menu_setter/__init__.py
menu_setter/__main__.py
menu_setter/commander.py
menu_setter/connector.py
menu_setter/core.py
menu_setter/exceptions.py
menu_setter/setter.py
menu_setter/modules/__init__.py
menu_setter/ms_config/__init__.py
menu_setter/ms_config/data_extractor.py
menu_setter/ms_config/extra_opt.py
ms_config/__init__.py
ms_config/data_extractor.py
ms_config/extra_opt.py
tests/__init__.py
tests/test_moveInMenu.py
menu_setter3-0.1.4.dist-info/LICENSE
menu_setter3-0.1.4.dist-info/METADATA
menu_setter3-0.1.4.dist-info/WHEEL
menu_setter3-0.1.4.dist-info/top_level.txt
menu_setter3-0.1.4.dist-info/RECORD
