Metadata-Version: 2.1
Name: menu_setter3
Version: 0.1.4
Summary: Dynamic menu for easier customization
Author: Parsa Ahmadian(PKPY)
Author-email: <p3ahmadian@gmail.com>
Keywords: python,menu,dynamic,dynamic menu,menu setter,python menu,terminal
Classifier: Development Status :: 1 - Planning
Classifier: Intended Audience :: Developers
Classifier: Programming Language :: Python :: 3
Classifier: Operating System :: Unix
Classifier: Operating System :: MacOS :: MacOS X
Classifier: Operating System :: Microsoft :: Windows
License-File: LICENSE
